parallel.py
easy_parallel-0.1.6.dist-info/LICENSE
easy_parallel-0.1.6.dist-info/METADATA
easy_parallel-0.1.6.dist-info/WHEEL
easy_parallel-0.1.6.dist-info/top_level.txt
easy_parallel-0.1.6.dist-info/RECORD
