Metadata-Version: 2.1
Name: easy-parallel
Version: 0.1.6
Summary: Parallel wrapper for easy multi-threading.
Home-page: https://github.com/raphtown/easy-parallel
Author: Raphael Townshend
Author-email: UNKNOWN
License: MIT
Platform: UNKNOWN
Requires-Dist: pathos
